stoppy/__init__.py
stoppy/stopwatch.py
stoppy-1.0.5.dist-info/LICENSE
stoppy-1.0.5.dist-info/METADATA
stoppy-1.0.5.dist-info/WHEEL
stoppy-1.0.5.dist-info/RECORD
