Metadata-Version: 2.1
Name: stoppy
Version: 1.0.5
Summary: A precise and lightweight stopwatch built on top of `perf_counter`, which can be used as a replacement for `perf_counter` that returns absolute time starting from zero.
Home-page: https://github.com/morefigs/stoppy
Author: morefigs
Requires-Python: >=3.7,<4.0
Classifier: Programming Language :: Python :: 3
Classifier: Programming Language :: Python :: 3.7
Classifier: Programming Language :: Python :: 3.8
Classifier: Programming Language :: Python :: 3.9
Classifier: Programming Language :: Python :: 3.10
Classifier: Programming Language :: Python :: 3.11
